validatesns
